networkifaces/___init__.py
networkifaces/network.py
networkifaces-1.1.7.dist-info/LICENSE
networkifaces-1.1.7.dist-info/METADATA
networkifaces-1.1.7.dist-info/WHEEL
networkifaces-1.1.7.dist-info/top_level.txt
networkifaces-1.1.7.dist-info/RECORD
